_tests/__init__.py
_tests/other_module.py
hparams/__init__.py
hparams/hparams.py
hparams/py.typed
defaults-0.3.0.dist-info/LICENSE
defaults-0.3.0.dist-info/METADATA
defaults-0.3.0.dist-info/WHEEL
defaults-0.3.0.dist-info/top_level.txt
defaults-0.3.0.dist-info/zip-safe
defaults-0.3.0.dist-info/RECORD
